Metadata-Version: 2.1
Name: file-alchemy
Version: 0.0.1
Summary: Library for managing files associated with sqlalchemy database
Home-page: https://github.com/StannisGr/file-alchemy
Author: StannisGr
Author-email: bvc344@gmail.com
License: Apache License 2.0
Keywords: file upload,file managment,sqlalchemy,flask
Platform: any
License-File: LICENSE
